conductor/main.py
ct_conductor-0.0.0.dist-info/entry_points.txt
ct_conductor-0.0.0.dist-info/WHEEL
ct_conductor-0.0.0.dist-info/METADATA
ct_conductor-0.0.0.dist-info/RECORD
