Metadata-Version: 2.1
Name: ct-conductor
Version: 0.0.0
Summary: An Orchestration Tool
Author: None
Requires-Python: >=3.9,<4.0
Classifier: Programming Language :: Python :: 3
Classifier: Programming Language :: Python :: 3.10
Classifier: Programming Language :: Python :: 3.9
